pyparagraph/__init__.py
pyparagraph/__main__.py
pyparagraph/font.py
pyparagraph/linebreak.py
pyparagraph/linked_list.py
pyparagraph/pyparagraph.py
pyparagraph/wordwrap.py
pyparagraph-0.0.7.dist-info/LICENSE.txt
pyparagraph-0.0.7.dist-info/METADATA
pyparagraph-0.0.7.dist-info/WHEEL
pyparagraph-0.0.7.dist-info/entry_points.txt
pyparagraph-0.0.7.dist-info/top_level.txt
pyparagraph-0.0.7.dist-info/RECORD
