Metadata-Version: 2.1
Name: pyparagraph
Version: 0.0.7
Summary: A library to do Knuth-Plass (aka TeX/LaTeX) text-wrapping, rendering the result as lines of text or in a specified font/size on a PIL image. PIL rendering optionally supports limited rich text (bold and/or italic) via <b> and <i> tags.
Author: Sumner Hayes
Project-URL: Homepage, https://gitlab.com/sumnerh1/pyparagraph
Project-URL: Repository, https://gitlab.com/sumnerh1/pyparagraph
Project-URL: Bug Tracker, https://gitlab.com/sumnerh1/pyparagraph/-/issues
Classifier: Programming Language :: Python :: 3
Classifier: License :: OSI Approved :: MIT License
Classifier: Operating System :: OS Independent
Classifier: Topic :: Text Processing
Requires-Python: >=3.7
License-File: LICENSE.txt
Requires-Dist: setuptools (>=50)
Requires-Dist: pillow
Requires-Dist: matplotlib
Requires-Dist: langcodes
Requires-Dist: pyhyphen
